incantor/__init__.py
incantor-0.0.1.dist-info/LICENSE
incantor-0.0.1.dist-info/METADATA
incantor-0.0.1.dist-info/WHEEL
incantor-0.0.1.dist-info/RECORD
